setup.cfg
setup.py
astkit/__init__.py
astkit/processor.py
astkit/render.py
astkit/rewrite.py
astkit/util.py
astkit.egg-info/PKG-INFO
astkit.egg-info/SOURCES.txt
astkit.egg-info/dependency_links.txt
astkit.egg-info/entry_points.txt
astkit.egg-info/not-zip-safe
astkit.egg-info/top_level.txt
astkit/compat/__ast__.py
astkit/compat/__init__.py
astkit/compat/py2.py
astkit/compat/py3.py