Metadata-Version: 1.0
Name: astkit
Version: 0.5.4
Summary: A collection of tools and utilities built on the ast (python >=  2.6) module.
Home-page: https://bitbucket.org/desmaj/astkit
Author: Matthew J Desmarais
Author-email: matthew.desmarais@gmail.com
License: GPL
Keywords: ast
Platform: UNKNOWN
